{"_type":"export","__export_format":4,"__export_date":"2021-09-12T21:52:05.740Z","__export_source":"insomnia.desktop.app:v2021.5.2","resources":[{"_id":"req_a171914b93dd439c999ddf58ebaacadd","parentId":"fld_5f6be655e32248c48aa63dd9f5ac4442","modified":1631476939794,"created":1631476910218,"url":"{{ _.FullUrl }}/Address/{% prompt 'Address Id', 'Address Id', '', '', false, true %}","name":"ById","description":"","method":"GET","body":{},"parameters":[],"headers":[],"authentication":{"type":"bearer","token":"{{ _.Token }}"},"metaSortKey":-1629863701997.25,"isPrivate":false,"settingStoreCookies":true,"settingSendCookies":true,"settingDisableRenderRequestBody":false,"settingEncodeUrl":true,"settingRebuildPath":true,"settingFollowRedirects":"global","_type":"request"},{"_id":"fld_5f6be655e32248c48aa63dd9f5ac4442","parentId":"wrk_b9cd374b67564d4487ced925cd82548f","modified":1631471438208,"created":1631471438208,"name":"Address","description":"","environment":{},"environmentPropertyOrder":null,"metaSortKey":-1631471438208,"_type":"request_group"},{"_id":"wrk_b9cd374b67564d4487ced925cd82548f","parentId":null,"modified":1629316767169,"created":1629316767169,"name":"zbw.Auftragsverwaltung.Api.yaml","description":"","scope":"design","_type":"workspace"},{"_id":"req_b18624945ec24f1b8ca969a04d01a160","parentId":"fld_5f6be655e32248c48aa63dd9f5ac4442","modified":1631471463530,"created":1631471453896,"url":"{{ _.FullUrl }}/Address","name":"List","description":"","method":"GET","body":{},"parameters":[],"headers":[],"authentication":{"type":"bearer","token":"{{ _.Token }}"},"metaSortKey":-1629863701947.25,"isPrivate":false,"settingStoreCookies":true,"settingSendCookies":true,"settingDisableRenderRequestBody":false,"settingEncodeUrl":true,"settingRebuildPath":true,"settingFollowRedirects":"global","_type":"request"},{"_id":"req_5baf327e2a014eec87299e106ae8b1de","parentId":"fld_5f6be655e32248c48aa63dd9f5ac4442","modified":1631482218094,"created":1631471494014,"url":"{{ _.FullUrl }}/Address","name":"Add","description":"","method":"POST","body":{"mimeType":"application/json","text":"{\n  \"customerId\": \"d6c98ff2-e376-4209-3a78-08d9763477f0\",\n  \"street\": \"string\",\n  \"number\": 0,\n  \"zip\": \"string\",\n  \"recipient\": \"string\",\n  \"location\": \"string\",\n  \"fullAddress\": \"string\"\n}"},"parameters":[],"headers":[{"name":"Content-Type","value":"application/json","id":"pair_d6fb76e561e04373b5a7587de7d03b49"}],"authentication":{"type":"bearer","token":"{{ _.Token }}"},"metaSortKey":-1629772634091.375,"isPrivate":false,"settingStoreCookies":true,"settingSendCookies":true,"settingDisableRenderRequestBody":false,"settingEncodeUrl":true,"settingRebuildPath":true,"settingFollowRedirects":"global","_type":"request"},{"_id":"req_604325b7152a45d1b7cb528391ad7728","parentId":"fld_5f6be655e32248c48aa63dd9f5ac4442","modified":1631482263028,"created":1631476995335,"url":"{{ _.FullUrl }}/Address","name":"Update","description":"","method":"PATCH","body":{"mimeType":"application/json","text":"{\n  \"id\": \"f4d19710-17f2-47c2-ba36-12758ecc16c4\",\n  \"customerId\": \"d6c98ff2-e376-4209-3a78-08d9763477f0\",\n  \"street\": \"string\",\n  \"number\": 0,\n  \"zip\": \"string\",\n  \"recipient\": \"string\",\n  \"location\": \"string\",\n  \"fullAddress\": null,\n  \"validFrom\": \"2021-09-12T21:30:19.1703573Z\"\n}"},"parameters":[],"headers":[{"name":"Content-Type","value":"application/json","id":"pair_d6fb76e561e04373b5a7587de7d03b49"}],"authentication":{"type":"bearer","token":"{{ _.Token }}"},"metaSortKey":-1629727100163.4375,"isPrivate":false,"settingStoreCookies":true,"settingSendCookies":true,"settingDisableRenderRequestBody":false,"settingEncodeUrl":true,"settingRebuildPath":true,"settingFollowRedirects":"global","_type":"request"},{"_id":"req_522f642eb2084a89add4c9a719482739","parentId":"fld_5f6be655e32248c48aa63dd9f5ac4442","modified":1631482753007,"created":1631477021609,"url":"{{ _.FullUrl }}/Address","name":"Delete","description":"","method":"DELETE","body":{},"parameters":[{"id":"pair_6b6d7c8e6a2d4b319cc2e8ed50760a84","name":"id","value":"{% prompt 'Address Id', 'Address Id', '', '', false, true %}","description":""}],"headers":[],"authentication":{"type":"bearer","token":"{{ _.Token }}"},"metaSortKey":-1629704333199.4688,"isPrivate":false,"settingStoreCookies":true,"settingSendCookies":true,"settingDisableRenderRequestBody":false,"settingEncodeUrl":true,"settingRebuildPath":true,"settingFollowRedirects":"global","_type":"request"},{"_id":"req_d130b1b9b5cb4e078111718e2445965c","parentId":"fld_bbcd77fbba7d4966885a646b764dc964","modified":1631478134311,"created":1631477472886,"url":"{{ _.FullUrl }}/Article/{% prompt 'Id', 'Id', '', '', false, true %}","name":"ById","description":"","method":"GET","body":{},"parameters":[],"headers":[],"authentication":{"type":"bearer","token":"{{ _.Token }}"},"metaSortKey":-1629863701972.25,"isPrivate":false,"settingStoreCookies":true,"settingSendCookies":true,"settingDisableRenderRequestBody":false,"settingEncodeUrl":true,"settingRebuildPath":true,"settingFollowRedirects":"global","_type":"request"},{"_id":"fld_bbcd77fbba7d4966885a646b764dc964","parentId":"wrk_b9cd374b67564d4487ced925cd82548f","modified":1631477441883,"created":1631477439050,"name":"Article","description":"","environment":{},"environmentPropertyOrder":null,"metaSortKey":-1630758626505.5,"_type":"request_group"},{"_id":"req_2ff669ae913b4badbe38624fae029da8","parentId":"fld_bbcd77fbba7d4966885a646b764dc964","modified":1631478719671,"created":1631477478536,"url":"{{ _.FullUrl }}/Article","name":"List","description":"","method":"GET","body":{},"parameters":[],"headers":[],"authentication":{"type":"bearer","token":"{{ _.Token }}"},"metaSortKey":-1629863701922.25,"isPrivate":false,"settingStoreCookies":true,"settingSendCookies":true,"settingDisableRenderRequestBody":false,"settingEncodeUrl":true,"settingRebuildPath":true,"settingFollowRedirects":"global","_type":"request"},{"_id":"req_8794dfac62bd4edcb2d6e7af8474c996","parentId":"fld_bbcd77fbba7d4966885a646b764dc964","modified":1631480816572,"created":1631477488721,"url":"{{ _.FullUrl }}/Article","name":"Add","description":"","method":"POST","body":{"mimeType":"application/json","text":"{\n  \"articleId\": \"007\",\n  \"name\": \"TetsArticle\",\n  \"price\": 0,\n  \"articleGroupId\": \"7c22500e-a265-48ee-1930-08d9762fa039\"\n}"},"parameters":[],"headers":[{"name":"Content-Type","value":"application/json","id":"pair_d6fb76e561e04373b5a7587de7d03b49"}],"authentication":{"type":"bearer","token":"{{ _.Token }}"},"metaSortKey":-1629863701872.25,"isPrivate":false,"settingStoreCookies":true,"settingSendCookies":true,"settingDisableRenderRequestBody":false,"settingEncodeUrl":true,"settingRebuildPath":true,"settingFollowRedirects":"global","_type":"request"},{"_id":"req_2b2e09db4aa246a5b3ac0a6e32bea068","parentId":"fld_bbcd77fbba7d4966885a646b764dc964","modified":1631480933233,"created":1631477493722,"url":"{{ _.FullUrl }}/Article","name":"Update","description":"","method":"PATCH","body":{"mimeType":"application/json","text":"{\n  \"id\": \"05168acd-6709-498e-8f9d-08d97631804d\",\n  \"articleId\": \"007\",\n  \"name\": \"TetsArticle1\",\n  \"price\": 0,\n  \"articleGroupId\": \"7c22500e-a265-48ee-1930-08d9762fa039\"\n}"},"parameters":[],"headers":[{"name":"Content-Type","value":"application/json","id":"pair_d6fb76e561e04373b5a7587de7d03b49"}],"authentication":{"type":"bearer","token":"{{ _.Token }}"},"metaSortKey":-1629863701822.25,"isPrivate":false,"settingStoreCookies":true,"settingSendCookies":true,"settingDisableRenderRequestBody":false,"settingEncodeUrl":true,"settingRebuildPath":true,"settingFollowRedirects":"global","_type":"request"},{"_id":"req_472a0a0c59214f1bbe2c99565617676d","parentId":"fld_bbcd77fbba7d4966885a646b764dc964","modified":1631480689826,"created":1631477498850,"url":"{{ _.FullUrl }}/Article","name":"Delete","description":"","method":"DELETE","body":{},"parameters":[{"id":"pair_6b6d7c8e6a2d4b319cc2e8ed50760a84","name":"id","value":"{% prompt 'Address Id', 'Address Id', '', '', false, true %}","description":""}],"headers":[],"authentication":{"type":"bearer","token":"{{ _.Token }}"},"metaSortKey":-1629863701772.25,"isPrivate":false,"settingStoreCookies":true,"settingSendCookies":true,"settingDisableRenderRequestBody":false,"settingEncodeUrl":true,"settingRebuildPath":true,"settingFollowRedirects":"global","_type":"request"},{"_id":"req_71ab9b4e105f48799415f4eb03ad598f","parentId":"fld_bc673ea5c4ab413db23ad9505a9bea32","modified":1631479054923,"created":1631477613336,"url":"{{ _.FullUrl }}/ArticleGroup/{% prompt 'Address Id', 'Address Id', '', '', false, true %}","name":"ById","description":"","method":"GET","body":{},"parameters":[],"headers":[],"authentication":{"type":"bearer","token":"{{ _.Token }}"},"metaSortKey":-1630224017928.625,"isPrivate":false,"settingStoreCookies":true,"settingSendCookies":true,"settingDisableRenderRequestBody":false,"settingEncodeUrl":true,"settingRebuildPath":true,"settingFollowRedirects":"global","_type":"request"},{"_id":"fld_bc673ea5c4ab413db23ad9505a9bea32","parentId":"wrk_b9cd374b67564d4487ced925cd82548f","modified":1631477522007,"created":1631477517394,"name":"ArticleGroup","description":"","environment":{},"environmentPropertyOrder":null,"metaSortKey":-1630402220654.25,"_type":"request_group"},{"_id":"req_e3299dfee4984021963b2d969811a1b8","parentId":"fld_bc673ea5c4ab413db23ad9505a9bea32","modified":1631479056499,"created":1631477608638,"url":"{{ _.FullUrl }}/ArticleGroup","name":"List","description":"","method":"GET","body":{},"parameters":[],"headers":[],"authentication":{"type":"bearer","token":"{{ _.Token }}"},"metaSortKey":-1630224017878.625,"isPrivate":false,"settingStoreCookies":true,"settingSendCookies":true,"settingDisableRenderRequestBody":false,"settingEncodeUrl":true,"settingRebuildPath":true,"settingFollowRedirects":"global","_type":"request"},{"_id":"req_cc0246b7ef0e4455b050c8a27a4472c5","parentId":"fld_bc673ea5c4ab413db23ad9505a9bea32","modified":1631479051596,"created":1631477598892,"url":"{{ _.FullUrl }}/ArticleGroup","name":"Add","description":"","method":"POST","body":{"mimeType":"application/json","text":"{\n \t\"id\": \"26935dda-99ed-4185-88b8-522a1af5f05a\",\n  \"name\": \"testGroup1\"\n}"},"parameters":[],"headers":[{"name":"Content-Type","value":"application/json","id":"pair_d6fb76e561e04373b5a7587de7d03b49"}],"authentication":{"type":"bearer","token":"{{ _.Token }}"},"metaSortKey":-1630224017828.625,"isPrivate":false,"settingStoreCookies":true,"settingSendCookies":true,"settingDisableRenderRequestBody":false,"settingEncodeUrl":true,"settingRebuildPath":true,"settingFollowRedirects":"global","_type":"request"},{"_id":"req_68b503d4522845ab9d576eecf899a711","parentId":"fld_bc673ea5c4ab413db23ad9505a9bea32","modified":1631480749122,"created":1631477594143,"url":"{{ _.FullUrl }}/ArticleGroup","name":"Update","description":"","method":"PATCH","body":{"mimeType":"application/json","text":"{\n  \"id\": \"7c22500e-a265-48ee-1930-08d9762fa039\",\n  \"name\": \"testGroup01\",\n  \"parentId\": null\n}"},"parameters":[],"headers":[{"name":"Content-Type","value":"application/json","id":"pair_d6fb76e561e04373b5a7587de7d03b49"}],"authentication":{"type":"bearer","token":"{{ _.Token }}"},"metaSortKey":-1630224017778.625,"isPrivate":false,"settingStoreCookies":true,"settingSendCookies":true,"settingDisableRenderRequestBody":false,"settingEncodeUrl":true,"settingRebuildPath":true,"settingFollowRedirects":"global","_type":"request"},{"_id":"req_4543b792cb6e4c6fae46c003d2ecebc5","parentId":"fld_bc673ea5c4ab413db23ad9505a9bea32","modified":1631479060142,"created":1631477586244,"url":"{{ _.FullUrl }}/ArticleGroup","name":"Delete","description":"","method":"DELETE","body":{},"parameters":[{"id":"pair_6b6d7c8e6a2d4b319cc2e8ed50760a84","name":"id","value":"{% prompt 'Address Id', 'Address Id', '', '', false, true %}","description":""}],"headers":[],"authentication":{"type":"bearer","token":"{{ _.Token }}"},"metaSortKey":-1630224017728.625,"isPrivate":false,"settingStoreCookies":true,"settingSendCookies":true,"settingDisableRenderRequestBody":false,"settingEncodeUrl":true,"settingRebuildPath":true,"settingFollowRedirects":"global","_type":"request"},{"_id":"req_fc181eba39a64d838385b728bf5e55f0","parentId":"fld_05eb7a3a96674010ae5aade400ba630d","modified":1631036871790,"created":1629317294812,"url":"{{ _.FullUrl }}/Auth/Login","name":"Login","description":"","method":"POST","body":{"mimeType":"application/json","text":"{\n\t\"username\": \"{{ _.Username }}\",\n\t\"password\": \"{{ _.Password }}\"\n}"},"parameters":[],"headers":[{"name":"Content-Type","value":"application/json","id":"pair_1c4418cf6ed14970bac81aecf04016dc"}],"authentication":{},"metaSortKey":-1629317294812,"isPrivate":false,"settingStoreCookies":true,"settingSendCookies":true,"settingDisableRenderRequestBody":false,"settingEncodeUrl":true,"settingRebuildPath":true,"settingFollowRedirects":"global","_type":"request"},{"_id":"fld_05eb7a3a96674010ae5aade400ba630d","parentId":"wrk_b9cd374b67564d4487ced925cd82548f","modified":1631477652591,"created":1629317268437,"name":"Auth","description":"","environment":{},"environmentPropertyOrder":null,"metaSortKey":-1630224017728.625,"_type":"request_group"},{"_id":"req_d68808461922460b90c779b5d2b93f8f","parentId":"fld_05eb7a3a96674010ae5aade400ba630d","modified":1631020892643,"created":1630863996489,"url":"{{ _.FullUrl }}/Auth/refresh-token","name":"Refresh-Token","description":"","method":"POST","body":{"mimeType":"application/json","text":"{\n\t\"Token\": \"OV2D4xXheftIbDiwNVCJraHogjg6EyH2Ms2iLgQIuqCyd9lQCyNytGdCHSXQLeNCbl/P6O7iCyBEeewckHTJ9w==\"\n}"},"parameters":[],"headers":[{"name":"Content-Type","value":"application/json","id":"pair_1c4418cf6ed14970bac81aecf04016dc"}],"authentication":{},"metaSortKey":-1629317294762,"isPrivate":false,"settingStoreCookies":true,"settingSendCookies":true,"settingDisableRenderRequestBody":false,"settingEncodeUrl":true,"settingRebuildPath":true,"settingFollowRedirects":"global","_type":"request"},{"_id":"req_c829ccbfcd11422bbfe6bd7c005cf8e6","parentId":"fld_05eb7a3a96674010ae5aade400ba630d","modified":1630864195652,"created":1630864188598,"url":"{{ _.FullUrl }}/Auth/revoke-token","name":"Revoke-Token","description":"","method":"POST","body":{"mimeType":"application/json","text":"{\n\t\"Token\": \"8Y3Sb61jKhB5VOGfwe0qZaq+NRnhbBYsfL6OCm00b6UZQxajaLWHgYpvzmsgeNcLWRDkIETFe6Jxn9BawAJ/Qg==\"\n}"},"parameters":[],"headers":[{"name":"Content-Type","value":"application/json","id":"pair_1c4418cf6ed14970bac81aecf04016dc"}],"authentication":{},"metaSortKey":-1629317294712,"isPrivate":false,"settingStoreCookies":true,"settingSendCookies":true,"settingDisableRenderRequestBody":false,"settingEncodeUrl":true,"settingRebuildPath":true,"settingFollowRedirects":"global","_type":"request"},{"_id":"req_2b80844157b841d08e949aa28b6920e4","parentId":"fld_c27c5dd830e84bf3bbb30d2b332ee6cf","modified":1631026235536,"created":1630045837659,"url":"{{ _.FullUrl }}/Customer/{% prompt 'Customer ID', 'ID', '', '', false, true %}","name":"ById","description":"","method":"GET","body":{},"parameters":[],"headers":[],"authentication":{"type":"bearer","token":"{{ _.Token }}"},"metaSortKey":-1630045837659,"isPrivate":false,"settingStoreCookies":true,"settingSendCookies":true,"settingDisableRenderRequestBody":false,"settingEncodeUrl":true,"settingRebuildPath":true,"settingFollowRedirects":"global","_type":"request"},{"_id":"fld_c27c5dd830e84bf3bbb30d2b332ee6cf","parentId":"wrk_b9cd374b67564d4487ced925cd82548f","modified":1630045814803,"created":1630045814803,"name":"Customers","description":"","environment":{},"environmentPropertyOrder":null,"metaSortKey":-1630045814803,"_type":"request_group"},{"_id":"req_47f3bd3ea2fc49bd8063f31b0192b932","parentId":"fld_c27c5dd830e84bf3bbb30d2b332ee6cf","modified":1631471645300,"created":1631471643026,"url":"{{ _.FullUrl }}/Customer","name":"List","description":"","method":"GET","body":{},"parameters":[],"headers":[],"authentication":{"type":"bearer","token":"{{ _.Token }}"},"metaSortKey":-1629954769803.125,"isPrivate":false,"settingStoreCookies":true,"settingSendCookies":true,"settingDisableRenderRequestBody":false,"settingEncodeUrl":true,"settingRebuildPath":true,"settingFollowRedirects":"global","_type":"request"},{"_id":"req_fd37ff1c46eb40cfa9eb16cf55651e05","parentId":"fld_c27c5dd830e84bf3bbb30d2b332ee6cf","modified":1631482196254,"created":1631025960198,"url":"{{ _.FullUrl }}/Customer","name":"Add","description":"","method":"POST","body":{"mimeType":"application/json","text":"{\n  \"customerNr\": \"CU00000\",\n  \"firstname\": \"test\",\n  \"lastname\": \"test\",\n  \"website\": \"http://www.google.ch\",\n  \"userId\": \"1AD8487A-E600-41CA-A1C6-08D9722263C8\"\n}"},"parameters":[],"headers":[{"name":"Content-Type","value":"application/json","id":"pair_496dd23f677e4bd98ba194588ced5e7c"}],"authentication":{"type":"bearer","token":"{{ _.Token }}"},"metaSortKey":-1629681566235.5,"isPrivate":false,"settingStoreCookies":true,"settingSendCookies":true,"settingDisableRenderRequestBody":false,"settingEncodeUrl":true,"settingRebuildPath":true,"settingFollowRedirects":"global","_type":"request"},{"_id":"req_68ba761cc6d84055ae50809088ad69b1","parentId":"fld_c27c5dd830e84bf3bbb30d2b332ee6cf","modified":1631481193254,"created":1631477661309,"url":"{{ _.FullUrl }}/Customer","name":"Update","description":"","method":"PATCH","body":{"mimeType":"application/json","text":"{\n  \"customerNr\": 0,\n  \"firstname\": \"test\",\n  \"lastname\": \"test\",\n  \"website\": \"test\",\n  \"userId\": \"1AD8487A-E600-41CA-A1C6-08D9722263C8\"\n}"},"parameters":[],"headers":[{"name":"Content-Type","value":"application/json","id":"pair_d6fb76e561e04373b5a7587de7d03b49"}],"authentication":{"type":"bearer","token":"{{ _.Token }}"},"metaSortKey":-1629681566185.5,"isPrivate":false,"settingStoreCookies":true,"settingSendCookies":true,"settingDisableRenderRequestBody":false,"settingEncodeUrl":true,"settingRebuildPath":true,"settingFollowRedirects":"global","_type":"request"},{"_id":"req_b9a569f531f34db8a4e0110221fe5ed9","parentId":"fld_c27c5dd830e84bf3bbb30d2b332ee6cf","modified":1631480735807,"created":1631477666051,"url":"{{ _.FullUrl }}/Customer","name":"Delete","description":"","method":"DELETE","body":{},"parameters":[{"id":"pair_6b6d7c8e6a2d4b319cc2e8ed50760a84","name":"id","value":"{% prompt 'Address Id', 'Address Id', '', '', false, true %}","description":""}],"headers":[],"authentication":{"type":"bearer","token":"{{ _.Token }}"},"metaSortKey":-1629681566135.5,"isPrivate":false,"settingStoreCookies":true,"settingSendCookies":true,"settingDisableRenderRequestBody":false,"settingEncodeUrl":true,"settingRebuildPath":true,"settingFollowRedirects":"global","_type":"request"},{"_id":"req_7334db7855ec4de6b1d15ccb71eae6ff","parentId":"fld_45b42ee2ba2f45c69c5b21407601d7dc","modified":1631482502279,"created":1631477697782,"url":"{{ _.FullUrl }}/Invoice/{% prompt 'Address Id', 'Address Id', '', '', false, true %}","name":"ById","description":"","method":"GET","body":{},"parameters":[],"headers":[],"authentication":{"type":"bearer","token":"{{ _.Token }}"},"metaSortKey":-1629692949917.4844,"isPrivate":false,"settingStoreCookies":true,"settingSendCookies":true,"settingDisableRenderRequestBody":false,"settingEncodeUrl":true,"settingRebuildPath":true,"settingFollowRedirects":"global","_type":"request"},{"_id":"fld_45b42ee2ba2f45c69c5b21407601d7dc","parentId":"wrk_b9cd374b67564d4487ced925cd82548f","modified":1631477676851,"created":1631477673449,"name":"Invoice","description":"","environment":{},"environmentPropertyOrder":null,"metaSortKey":-1630045814753,"_type":"request_group"},{"_id":"req_4bd6ba4d14a7435f85baf2c8176cfe49","parentId":"fld_45b42ee2ba2f45c69c5b21407601d7dc","modified":1631482505395,"created":1631477694060,"url":"{{ _.FullUrl }}/Invoice","name":"List","description":"","method":"GET","body":{},"parameters":[],"headers":[],"authentication":{"type":"bearer","token":"{{ _.Token }}"},"metaSortKey":-1629692949867.4844,"isPrivate":false,"settingStoreCookies":true,"settingSendCookies":true,"settingDisableRenderRequestBody":false,"settingEncodeUrl":true,"settingRebuildPath":true,"settingFollowRedirects":"global","_type":"request"},{"_id":"req_7f34c560e2064892bc2b5eea0bbc4313","parentId":"fld_45b42ee2ba2f45c69c5b21407601d7dc","modified":1631482514834,"created":1631477690331,"url":"{{ _.FullUrl }}/Invoice","name":"Add","description":"","method":"POST","body":{"mimeType":"application/json","text":"{\n  \"addressId\": \"f4d19710-17f2-47c2-ba36-12758ecc16c4\",\n  \"date\": \"2021-09-12T21:32:16.147Z\",\n  \"number\": 100,\n  \"netto\": 100,\n  \"brutto\": 100,\n  \"tax\": 2,\n  \"adressValidFrom\": \"2021-09-12T21:30:19.1703573\"\n}"},"parameters":[],"headers":[{"name":"Content-Type","value":"application/json","id":"pair_d6fb76e561e04373b5a7587de7d03b49"}],"authentication":{"type":"bearer","token":"{{ _.Token }}"},"metaSortKey":-1629692949817.4844,"isPrivate":false,"settingStoreCookies":true,"settingSendCookies":true,"settingDisableRenderRequestBody":false,"settingEncodeUrl":true,"settingRebuildPath":true,"settingFollowRedirects":"global","_type":"request"},{"_id":"req_8dd5473fd78a4bcc99c26e90e2495908","parentId":"fld_45b42ee2ba2f45c69c5b21407601d7dc","modified":1631482537520,"created":1631477684510,"url":"{{ _.FullUrl }}/Invoice","name":"Update","description":"","method":"PATCH","body":{"mimeType":"application/json","text":"{\n  \"id\": \"2cab0d04-bb95-4724-31c8-08d976353867\",\n  \"addressId\": \"f4d19710-17f2-47c2-ba36-12758ecc16c4\",\n  \"date\": \"2021-09-12T21:32:16.147Z\",\n  \"number\": 101,\n  \"netto\": 100,\n  \"brutto\": 100,\n  \"tax\": 2,\n  \"adressValidFrom\": \"2021-09-12T21:30:19.1703573\"\n}"},"parameters":[],"headers":[{"name":"Content-Type","value":"application/json","id":"pair_d6fb76e561e04373b5a7587de7d03b49"}],"authentication":{"type":"bearer","token":"{{ _.Token }}"},"metaSortKey":-1629692949767.4844,"isPrivate":false,"settingStoreCookies":true,"settingSendCookies":true,"settingDisableRenderRequestBody":false,"settingEncodeUrl":true,"settingRebuildPath":true,"settingFollowRedirects":"global","_type":"request"},{"_id":"req_39a51bd78f03413f99b8341ac31e63a5","parentId":"fld_45b42ee2ba2f45c69c5b21407601d7dc","modified":1631482511072,"created":1631477680818,"url":"{{ _.FullUrl }}/Invoice","name":"Delete","description":"","method":"DELETE","body":{},"parameters":[{"id":"pair_6b6d7c8e6a2d4b319cc2e8ed50760a84","name":"id","value":"{% prompt 'Address Id', 'Address Id', '', '', false, true %}","description":""}],"headers":[],"authentication":{"type":"bearer","token":"{{ _.Token }}"},"metaSortKey":-1629692949717.4844,"isPrivate":false,"settingStoreCookies":true,"settingSendCookies":true,"settingDisableRenderRequestBody":false,"settingEncodeUrl":true,"settingRebuildPath":true,"settingFollowRedirects":"global","_type":"request"},{"_id":"req_13a6e3dd33204f1e9f1541102c7fde8c","parentId":"fld_a394f8eab17f4fb8a592de97c9236c5d","modified":1631482685018,"created":1631477776913,"url":"{{ _.FullUrl }}/Order/{% prompt 'Address Id', 'Address Id', '', '', false, true %}","name":"ById","description":"","method":"GET","body":{},"parameters":[],"headers":[],"authentication":{"type":"bearer","token":"{{ _.Token }}"},"metaSortKey":-1629698641758.4766,"isPrivate":false,"settingStoreCookies":true,"settingSendCookies":true,"settingDisableRenderRequestBody":false,"settingEncodeUrl":true,"settingRebuildPath":true,"settingFollowRedirects":"global","_type":"request"},{"_id":"fld_a394f8eab17f4fb8a592de97c9236c5d","parentId":"wrk_b9cd374b67564d4487ced925cd82548f","modified":1631477711553,"created":1631477708133,"name":"Order","description":"","environment":{},"environmentPropertyOrder":null,"metaSortKey":-1630045814703,"_type":"request_group"},{"_id":"req_252c10c2f4d94643824c30a6e04eb25a","parentId":"fld_a394f8eab17f4fb8a592de97c9236c5d","modified":1631482699743,"created":1631477772197,"url":"{{ _.FullUrl }}/Order","name":"List","description":"","method":"GET","body":{},"parameters":[],"headers":[],"authentication":{"type":"bearer","token":"{{ _.Token }}"},"metaSortKey":-1629698641708.4766,"isPrivate":false,"settingStoreCookies":true,"settingSendCookies":true,"settingDisableRenderRequestBody":false,"settingEncodeUrl":true,"settingRebuildPath":true,"settingFollowRedirects":"global","_type":"request"},{"_id":"req_ad7454bb231a4a568cf10d74c3cf5b7b","parentId":"fld_a394f8eab17f4fb8a592de97c9236c5d","modified":1631482681803,"created":1631477766502,"url":"{{ _.FullUrl }}/Order","name":"Add","description":"","method":"POST","body":{"mimeType":"application/json","text":"{\n  \"orderNr\": 1,\n  \"customerId\": \"d6c98ff2-e376-4209-3a78-08d9763477f0\",\n  \"date\": \"2021-09-12T21:35:52.936Z\"\n}"},"parameters":[],"headers":[{"name":"Content-Type","value":"application/json","id":"pair_d6fb76e561e04373b5a7587de7d03b49"}],"authentication":{"type":"bearer","token":"{{ _.Token }}"},"metaSortKey":-1629698641658.4766,"isPrivate":false,"settingStoreCookies":true,"settingSendCookies":true,"settingDisableRenderRequestBody":false,"settingEncodeUrl":true,"settingRebuildPath":true,"settingFollowRedirects":"global","_type":"request"},{"_id":"req_5dcb460f74484ceb8377ba0375b9c53e","parentId":"fld_a394f8eab17f4fb8a592de97c9236c5d","modified":1631482987598,"created":1631477761393,"url":"{{ _.FullUrl }}/Order","name":"Update","description":"","method":"PATCH","body":{"mimeType":"application/json","text":"{\n  \"id\": \"abde045d-1031-4a95-29cd-08d9763641a1\",\n  \"orderNr\": 2,\n  \"customerId\": \"d6c98ff2-e376-4209-3a78-08d9763477f0\",\n  \"date\": \"2021-09-12T21:35:52.936Z\"\n}"},"parameters":[],"headers":[{"name":"Content-Type","value":"application/json","id":"pair_d6fb76e561e04373b5a7587de7d03b49"}],"authentication":{"type":"bearer","token":"{{ _.Token }}"},"metaSortKey":-1629698641608.4766,"isPrivate":false,"settingStoreCookies":true,"settingSendCookies":true,"settingDisableRenderRequestBody":false,"settingEncodeUrl":true,"settingRebuildPath":true,"settingFollowRedirects":"global","_type":"request"},{"_id":"req_f8f7693905594d05a58be9dd83f5753d","parentId":"fld_a394f8eab17f4fb8a592de97c9236c5d","modified":1631482705794,"created":1631477757024,"url":"{{ _.FullUrl }}/Order","name":"Delete","description":"","method":"DELETE","body":{},"parameters":[{"id":"pair_6b6d7c8e6a2d4b319cc2e8ed50760a84","name":"id","value":"{% prompt 'Address Id', 'Address Id', '', '', false, true %}","description":""}],"headers":[],"authentication":{"type":"bearer","token":"{{ _.Token }}"},"metaSortKey":-1629698641558.4766,"isPrivate":false,"settingStoreCookies":true,"settingSendCookies":true,"settingDisableRenderRequestBody":false,"settingEncodeUrl":true,"settingRebuildPath":true,"settingFollowRedirects":"global","_type":"request"},{"_id":"req_10038b5bd25d406d9b7baf9a243f1742","parentId":"fld_90a44de19d5b414fa9004eeefe10fd05","modified":1631483092961,"created":1631477818995,"url":"{{ _.FullUrl }}/Position/{% prompt 'Address Id', 'Address Id', '', '', false, true %}","name":"ById","description":"","method":"GET","body":{},"parameters":[],"headers":[],"authentication":{"type":"bearer","token":"{{ _.Token }}"},"metaSortKey":-1629863701984.75,"isPrivate":false,"settingStoreCookies":true,"settingSendCookies":true,"settingDisableRenderRequestBody":false,"settingEncodeUrl":true,"settingRebuildPath":true,"settingFollowRedirects":"global","_type":"request"},{"_id":"fld_90a44de19d5b414fa9004eeefe10fd05","parentId":"wrk_b9cd374b67564d4487ced925cd82548f","modified":1631477797643,"created":1631477794463,"name":"Position","description":"","environment":{},"environmentPropertyOrder":null,"metaSortKey":-1630045814653,"_type":"request_group"},{"_id":"req_47a24c26107541d6b747855c584be6d1","parentId":"fld_90a44de19d5b414fa9004eeefe10fd05","modified":1631483094876,"created":1631477825165,"url":"{{ _.FullUrl }}/Position","name":"List","description":"","method":"GET","body":{},"parameters":[],"headers":[],"authentication":{"type":"bearer","token":"{{ _.Token }}"},"metaSortKey":-1629863701934.75,"isPrivate":false,"settingStoreCookies":true,"settingSendCookies":true,"settingDisableRenderRequestBody":false,"settingEncodeUrl":true,"settingRebuildPath":true,"settingFollowRedirects":"global","_type":"request"},{"_id":"req_4299e9a848e74d1f9dbfbb085be97329","parentId":"fld_90a44de19d5b414fa9004eeefe10fd05","modified":1631483089335,"created":1631477829539,"url":"{{ _.FullUrl }}/Position","name":"Add","description":"","method":"POST","body":{"mimeType":"application/json","text":"{\n  \"nr\": 1,\n  \"articleId\": \"05168acd-6709-498e-8f9d-08d97631804d\",\n  \"amount\": 1\n}"},"parameters":[],"headers":[{"name":"Content-Type","value":"application/json","id":"pair_d6fb76e561e04373b5a7587de7d03b49"}],"authentication":{"type":"bearer","token":"{{ _.Token }}"},"metaSortKey":-1629863701884.75,"isPrivate":false,"settingStoreCookies":true,"settingSendCookies":true,"settingDisableRenderRequestBody":false,"settingEncodeUrl":true,"settingRebuildPath":true,"settingFollowRedirects":"global","_type":"request"},{"_id":"req_7c3e0888b4114c0982b70e79fb0147a0","parentId":"fld_90a44de19d5b414fa9004eeefe10fd05","modified":1631483116042,"created":1631477833944,"url":"{{ _.FullUrl }}/Position","name":"Update","description":"","method":"PATCH","body":{"mimeType":"application/json","text":"{\n  \"id\": \"1b4dfdb2-1d47-427d-5fbd-08d976369757\",\n  \"nr\": 2,\n  \"articleId\": \"05168acd-6709-498e-8f9d-08d97631804d\",\n  \"amount\": 1\n}"},"parameters":[],"headers":[{"name":"Content-Type","value":"application/json","id":"pair_d6fb76e561e04373b5a7587de7d03b49"}],"authentication":{"type":"bearer","token":"{{ _.Token }}"},"metaSortKey":-1629863701834.75,"isPrivate":false,"settingStoreCookies":true,"settingSendCookies":true,"settingDisableRenderRequestBody":false,"settingEncodeUrl":true,"settingRebuildPath":true,"settingFollowRedirects":"global","_type":"request"},{"_id":"req_1819cbe625e94878ad4ce14e188592aa","parentId":"fld_90a44de19d5b414fa9004eeefe10fd05","modified":1631483100525,"created":1631477837711,"url":"{{ _.FullUrl }}/Position","name":"Delete","description":"","method":"DELETE","body":{},"parameters":[{"id":"pair_6b6d7c8e6a2d4b319cc2e8ed50760a84","name":"id","value":"{% prompt 'Address Id', 'Address Id', '', '', false, true %}","description":""}],"headers":[],"authentication":{"type":"bearer","token":"{{ _.Token }}"},"metaSortKey":-1629863701784.75,"isPrivate":false,"settingStoreCookies":true,"settingSendCookies":true,"settingDisableRenderRequestBody":false,"settingEncodeUrl":true,"settingRebuildPath":true,"settingFollowRedirects":"global","_type":"request"},{"_id":"req_753e21a980b747f186ab07872873eeb1","parentId":"fld_0bc5ce0659674bd08f2488c415c3a2cc","modified":1631483175766,"created":1631477858604,"url":"{{ _.FullUrl }}/Report/CTE","name":"CTE","description":"","method":"GET","body":{},"parameters":[],"headers":[],"authentication":{"type":"bearer","token":"{{ _.Token }}"},"metaSortKey":-1629863701991,"isPrivate":false,"settingStoreCookies":true,"settingSendCookies":true,"settingDisableRenderRequestBody":false,"settingEncodeUrl":true,"settingRebuildPath":true,"settingFollowRedirects":"global","_type":"request"},{"_id":"fld_0bc5ce0659674bd08f2488c415c3a2cc","parentId":"wrk_b9cd374b67564d4487ced925cd82548f","modified":1631477854199,"created":1631477852054,"name":"Report","description":"","environment":{},"environmentPropertyOrder":null,"metaSortKey":-1630045814603,"_type":"request_group"},{"_id":"req_456ca7b6a78044eda7101274b314de32","parentId":"fld_0bc5ce0659674bd08f2488c415c3a2cc","modified":1631483202335,"created":1631477866437,"url":"{{ _.FullUrl }}/Report/Faktura","name":"Faktura","description":"","method":"GET","body":{},"parameters":[],"headers":[],"authentication":{"type":"bearer","token":"{{ _.Token }}"},"metaSortKey":-1629863701987.875,"isPrivate":false,"settingStoreCookies":true,"settingSendCookies":true,"settingDisableRenderRequestBody":false,"settingEncodeUrl":true,"settingRebuildPath":true,"settingFollowRedirects":"global","_type":"request"},{"_id":"req_be5ca4ea9c0b4159bb648542735caa3b","parentId":"fld_486ec8bb64ee43c593b617af0f67420c","modified":1631483138529,"created":1631477894282,"url":"{{ _.FullUrl }}/User/{% prompt 'Address Id', 'Address Id', '', '', false, true %}","name":"ById","description":"","method":"GET","body":{},"parameters":[],"headers":[],"authentication":{"type":"bearer","token":"{{ _.Token }}"},"metaSortKey":-1629863701994.125,"isPrivate":false,"settingStoreCookies":true,"settingSendCookies":true,"settingDisableRenderRequestBody":false,"settingEncodeUrl":true,"settingRebuildPath":true,"settingFollowRedirects":"global","_type":"request"},{"_id":"fld_486ec8bb64ee43c593b617af0f67420c","parentId":"wrk_b9cd374b67564d4487ced925cd82548f","modified":1631477875140,"created":1631477873021,"name":"User","description":"","environment":{},"environmentPropertyOrder":null,"metaSortKey":-1630045814553,"_type":"request_group"},{"_id":"req_400e6dfc38fb406cab3808a24f9ef036","parentId":"fld_486ec8bb64ee43c593b617af0f67420c","modified":1631483147575,"created":1631477900104,"url":"{{ _.FullUrl }}/User","name":"Update","description":"","method":"PATCH","body":{"mimeType":"application/json","text":"{\n  \"id\": \"3ce735e2-7f81-4a08-a373-04e31bade7e3\",\n  \"customerId\": \"17269cf3-39b8-4022-0987-08d97227a08b\",\n  \"street\": \"string\",\n  \"number\": 0,\n  \"zip\": \"string\",\n  \"recipient\": \"string\",\n  \"location\": \"string\",\n  \"fullAddress\": null,\n  \"validFrom\": \"2021-09-12T18:35:08.9717285Z\"\n}"},"parameters":[],"headers":[{"name":"Content-Type","value":"application/json","id":"pair_d6fb76e561e04373b5a7587de7d03b49"}],"authentication":{"type":"bearer","token":"{{ _.Token }}"},"metaSortKey":-1629863701944.125,"isPrivate":false,"settingStoreCookies":true,"settingSendCookies":true,"settingDisableRenderRequestBody":false,"settingEncodeUrl":true,"settingRebuildPath":true,"settingFollowRedirects":"global","_type":"request"},{"_id":"req_2ab58b9ac0764cb79741ca94333ed1be","parentId":"fld_486ec8bb64ee43c593b617af0f67420c","modified":1631483150744,"created":1631477904829,"url":"{{ _.FullUrl }}/User","name":"Delete","description":"","method":"DELETE","body":{},"parameters":[{"id":"pair_6b6d7c8e6a2d4b319cc2e8ed50760a84","name":"id","value":"{% prompt 'Address Id', 'Address Id', '', '', false, true %}","description":""}],"headers":[],"authentication":{"type":"bearer","token":"{{ _.Token }}"},"metaSortKey":-1629863701894.125,"isPrivate":false,"settingStoreCookies":true,"settingSendCookies":true,"settingDisableRenderRequestBody":false,"settingEncodeUrl":true,"settingRebuildPath":true,"settingFollowRedirects":"global","_type":"request"},{"_id":"env_28900db254353dc1291e02c305f0840509756016","parentId":"wrk_b9cd374b67564d4487ced925cd82548f","modified":1631026033197,"created":1629316767314,"name":"Base Environment","data":{"BaseUrl":"","ApiEndpoint":"/api","FullUrl":"{{ _.BaseUrl }}{{ _.ApiEndpoint }}","Username":"","Password":"","Token":"{% response 'body', 'req_fc181eba39a64d838385b728bf5e55f0', 'b64::JC5hdXRoZW50aWNhdGlvblRva2Vu::46b', 'when-expired', 60 %}"},"dataPropertyOrder":{"&":["BaseUrl","ApiEndpoint","FullUrl","Username","Password","Token"]},"color":null,"isPrivate":false,"metaSortKey":1629316767314,"_type":"environment"},{"_id":"jar_28900db254353dc1291e02c305f0840509756016","parentId":"wrk_b9cd374b67564d4487ced925cd82548f","modified":1631483440574,"created":1629316767316,"name":"Default Jar","cookies":[{"key":".AspNetCore.Identity.Application","value":"CfDJ8F83hwldJkdDmWNljkwQIi2z7JMs4uzA7on7CjmqmtZk6UItXWc_GEltS-C_W7CkqjdRvvCUUxQZ-f0bXgTPguvae75CKoyGOxF7RbcEALN2g3Q4TdevBdvJZ1BLBQgwg_-P3mMmCNG0K9Z8aT5cktA1qt-1cs6JjWYlaZu-DblR45aGtx8tvFErTjTqW87jJrwyU6U1GexduE8MvfNy2fQA8ZxK4cAiySBvbkh19TZiPNEUhk2jKGidPqSKQtNPkITlOiBqgJ1mQKJ3F9DpMm8Gc2FTGqJWzN4X3AM6EYX_PvBnVtKrVKS02DGbg10zN4HeWX_W2jUVDsq0rickCCakKBM6tfXxvX9UFdSzy0617OrynPZsoZHIkKfrq4B5ir2e7nZigZH2UHbWbCvI4KhfTagWuTvnj_62kHN199Fg4Ol_6KFgbRAeKfXNyrDPHfObwmxixDPUu3bL8GYxn4xvrTfXsjRgf-vc7ubEIzj6-WDQ0JQYKoBp6IxB0Pprvlq8gK7ZccHQc9_KLaWM8mTW9DyYUKUDFt00lL5dGkUroW1qCymhDTTbi8QK_XDbcbYhzpJS4XWoxX7X8yGIx-UF0vSekCFBB-bq-F2yXWNCKZQSEW7ZshyzeUc7EIGmVWAcWkcGTwnmjovjMlbpTwRV49ctx7EL6lY2QVJ-tZBMBq00wCmpkMVi81acNs-y-EtpBv0ClMSrlf0jk2mNnleTKq-jX5dmXDwm725FGX7U","domain":"localhost","path":"/","httpOnly":true,"extensions":["samesite=lax"],"hostOnly":true,"creation":"2021-08-18T20:18:06.318Z","lastAccessed":"2021-09-12T21:50:40.574Z","id":"46027546442041367"}],"_type":"cookie_jar"},{"_id":"spc_c752c66c2522401ba3c540762220c9d6","parentId":"wrk_b9cd374b67564d4487ced925cd82548f","modified":1629316796915,"created":1629316767174,"fileName":"zbw.Auftragsverwaltung.Api.yaml","contents":"{\n  \"openapi\": \"3.0.1\",\n  \"info\": {\n    \"title\": \"zbw.Auftragsverwaltung.Api\",\n    \"version\": \"1.0\"\n  },\n  \"paths\": {\n    \"/api/ArticleGroup\": {\n      \"get\": {\n        \"tags\": [\n          \"ArticleGroup\"\n        ],\n        \"parameters\": [\n          {\n            \"name\": \"size\",\n            \"in\": \"query\",\n            \"schema\": {\n              \"type\": \"integer\",\n              \"format\": \"int32\",\n              \"default\": 10\n            }\n          },\n          {\n            \"name\": \"page\",\n            \"in\": \"query\",\n            \"schema\": {\n              \"type\": \"integer\",\n              \"format\": \"int32\",\n              \"default\": 1\n            }\n          },\n          {\n            \"name\": \"deleted\",\n            \"in\": \"query\",\n            \"schema\": {\n              \"type\": \"boolean\",\n              \"default\": false\n            }\n          }\n        ],\n        \"responses\": {\n          \"200\": {\n            \"description\": \"Success\",\n            \"content\": {\n              \"text/plain\": {\n                \"schema\": {\n                  \"$ref\": \"#/components/schemas/ArticleGroupDtoPaginatedList\"\n                }\n              },\n              \"application/json\": {\n                \"schema\": {\n                  \"$ref\": \"#/components/schemas/ArticleGroupDtoPaginatedList\"\n                }\n              },\n              \"text/json\": {\n                \"schema\": {\n                  \"$ref\": \"#/components/schemas/ArticleGroupDtoPaginatedList\"\n                }\n              }\n            }\n          }\n        }\n      },\n      \"post\": {\n        \"tags\": [\n          \"ArticleGroup\"\n        ],\n        \"requestBody\": {\n          \"content\": {\n            \"application/json\": {\n              \"schema\": {\n                \"$ref\": \"#/components/schemas/ArticleGroupDto\"\n              }\n            },\n            \"text/json\": {\n              \"schema\": {\n                \"$ref\": \"#/components/schemas/ArticleGroupDto\"\n              }\n            },\n            \"application/*+json\": {\n              \"schema\": {\n                \"$ref\": \"#/components/schemas/ArticleGroupDto\"\n              }\n            }\n          }\n        },\n        \"responses\": {\n          \"200\": {\n            \"description\": \"Success\",\n            \"content\": {\n              \"text/plain\": {\n                \"schema\": {\n                  \"$ref\": \"#/components/schemas/ArticleGroupDto\"\n                }\n              },\n              \"application/json\": {\n                \"schema\": {\n                  \"$ref\": \"#/components/schemas/ArticleGroupDto\"\n                }\n              },\n              \"text/json\": {\n                \"schema\": {\n                  \"$ref\": \"#/components/schemas/ArticleGroupDto\"\n                }\n              }\n            }\n          }\n        }\n      },\n      \"patch\": {\n        \"tags\": [\n          \"ArticleGroup\"\n        ],\n        \"requestBody\": {\n          \"content\": {\n            \"application/json\": {\n              \"schema\": {\n                \"$ref\": \"#/components/schemas/ArticleGroupDto\"\n              }\n            },\n            \"text/json\": {\n              \"schema\": {\n                \"$ref\": \"#/components/schemas/ArticleGroupDto\"\n              }\n            },\n            \"application/*+json\": {\n              \"schema\": {\n                \"$ref\": \"#/components/schemas/ArticleGroupDto\"\n              }\n            }\n          }\n        },\n        \"responses\": {\n          \"200\": {\n            \"description\": \"Success\",\n            \"content\": {\n              \"text/plain\": {\n                \"schema\": {\n                  \"$ref\": \"#/components/schemas/ArticleGroupDto\"\n                }\n              },\n              \"application/json\": {\n                \"schema\": {\n                  \"$ref\": \"#/components/schemas/ArticleGroupDto\"\n                }\n              },\n              \"text/json\": {\n                \"schema\": {\n                  \"$ref\": \"#/components/schemas/ArticleGroupDto\"\n                }\n              }\n            }\n          }\n        }\n      },\n      \"delete\": {\n        \"tags\": [\n          \"ArticleGroup\"\n        ],\n        \"parameters\": [\n          {\n            \"name\": \"id\",\n            \"in\": \"query\",\n            \"schema\": {\n              \"type\": \"string\",\n              \"format\": \"uuid\"\n            }\n          }\n        ],\n        \"responses\": {\n          \"200\": {\n            \"description\": \"Success\"\n          }\n        }\n      }\n    },\n    \"/api/ArticleGroup/{id}\": {\n      \"get\": {\n        \"tags\": [\n          \"ArticleGroup\"\n        ],\n        \"parameters\": [\n          {\n            \"name\": \"id\",\n            \"in\": \"path\",\n            \"required\": true,\n            \"schema\": {\n              \"type\": \"string\",\n              \"format\": \"uuid\"\n            }\n          }\n        ],\n        \"responses\": {\n          \"200\": {\n            \"description\": \"Success\",\n            \"content\": {\n              \"text/plain\": {\n                \"schema\": {\n                  \"$ref\": \"#/components/schemas/ArticleGroupDtoPaginatedList\"\n                }\n              },\n              \"application/json\": {\n                \"schema\": {\n                  \"$ref\": \"#/components/schemas/ArticleGroupDtoPaginatedList\"\n                }\n              },\n              \"text/json\": {\n                \"schema\": {\n                  \"$ref\": \"#/components/schemas/ArticleGroupDtoPaginatedList\"\n                }\n              }\n            }\n          }\n        }\n      }\n    },\n    \"/api/Auth/Register\": {\n      \"post\": {\n        \"tags\": [\n          \"Auth\"\n        ],\n        \"requestBody\": {\n          \"content\": {\n            \"application/json\": {\n              \"schema\": {\n                \"$ref\": \"#/components/schemas/UserDetails\"\n              }\n            },\n            \"text/json\": {\n              \"schema\": {\n                \"$ref\": \"#/components/schemas/UserDetails\"\n              }\n            },\n            \"application/*+json\": {\n              \"schema\": {\n                \"$ref\": \"#/components/schemas/UserDetails\"\n              }\n            }\n          }\n        },\n        \"responses\": {\n          \"200\": {\n            \"description\": \"Success\",\n            \"content\": {\n              \"text/plain\": {\n                \"schema\": {\n                  \"$ref\": \"#/components/schemas/SuccessMessage\"\n                }\n              },\n              \"application/json\": {\n                \"schema\": {\n                  \"$ref\": \"#/components/schemas/SuccessMessage\"\n                }\n              },\n              \"text/json\": {\n                \"schema\": {\n                  \"$ref\": \"#/components/schemas/SuccessMessage\"\n                }\n              }\n            }\n          }\n        }\n      }\n    },\n    \"/api/Auth/Login\": {\n      \"post\": {\n        \"tags\": [\n          \"Auth\"\n        ],\n        \"requestBody\": {\n          \"content\": {\n            \"application/json\": {\n              \"schema\": {\n                \"$ref\": \"#/components/schemas/Credentials\"\n              }\n            },\n            \"text/json\": {\n              \"schema\": {\n                \"$ref\": \"#/components/schemas/Credentials\"\n              }\n            },\n            \"application/*+json\": {\n              \"schema\": {\n                \"$ref\": \"#/components/schemas/Credentials\"\n              }\n            }\n          }\n        },\n        \"responses\": {\n          \"200\": {\n            \"description\": \"Success\",\n            \"content\": {\n              \"text/plain\": {\n                \"schema\": {\n                  \"$ref\": \"#/components/schemas/AuthenticatedMessage\"\n                }\n              },\n              \"application/json\": {\n                \"schema\": {\n                  \"$ref\": \"#/components/schemas/AuthenticatedMessage\"\n                }\n              },\n              \"text/json\": {\n                \"schema\": {\n                  \"$ref\": \"#/components/schemas/AuthenticatedMessage\"\n                }\n              }\n            }\n          }\n        }\n      }\n    },\n    \"/api/Auth/Logout\": {\n      \"post\": {\n        \"tags\": [\n          \"Auth\"\n        ],\n        \"responses\": {\n          \"200\": {\n            \"description\": \"Success\"\n          }\n        }\n      }\n    },\n    \"/api/Customer/{id}\": {\n      \"get\": {\n        \"tags\": [\n          \"Customer\"\n        ],\n        \"parameters\": [\n          {\n            \"name\": \"id\",\n            \"in\": \"path\",\n            \"required\": true,\n            \"schema\": {\n              \"type\": \"string\",\n              \"format\": \"uuid\"\n            }\n          }\n        ],\n        \"responses\": {\n          \"200\": {\n            \"description\": \"Success\",\n            \"content\": {\n              \"text/plain\": {\n                \"schema\": {\n                  \"$ref\": \"#/components/schemas/CustomerDto\"\n                }\n              },\n              \"application/json\": {\n                \"schema\": {\n                  \"$ref\": \"#/components/schemas/CustomerDto\"\n                }\n              },\n              \"text/json\": {\n                \"schema\": {\n                  \"$ref\": \"#/components/schemas/CustomerDto\"\n                }\n              }\n            }\n          }\n        }\n      }\n    },\n    \"/api/Customer\": {\n      \"get\": {\n        \"tags\": [\n          \"Customer\"\n        ],\n        \"parameters\": [\n          {\n            \"name\": \"size\",\n            \"in\": \"query\",\n            \"schema\": {\n              \"type\": \"integer\",\n              \"format\": \"int32\",\n              \"default\": 10\n            }\n          },\n          {\n            \"name\": \"page\",\n            \"in\": \"query\",\n            \"schema\": {\n              \"type\": \"integer\",\n              \"format\": \"int32\",\n              \"default\": 1\n            }\n          },\n          {\n            \"name\": \"deleted\",\n            \"in\": \"query\",\n            \"schema\": {\n              \"type\": \"boolean\",\n              \"default\": false\n            }\n          }\n        ],\n        \"responses\": {\n          \"200\": {\n            \"description\": \"Success\",\n            \"content\": {\n              \"text/plain\": {\n                \"schema\": {\n                  \"$ref\": \"#/components/schemas/CustomerDtoPaginatedList\"\n                }\n              },\n              \"application/json\": {\n                \"schema\": {\n                  \"$ref\": \"#/components/schemas/CustomerDtoPaginatedList\"\n                }\n              },\n              \"text/json\": {\n                \"schema\": {\n                  \"$ref\": \"#/components/schemas/CustomerDtoPaginatedList\"\n                }\n              }\n            }\n          }\n        }\n      },\n      \"post\": {\n        \"tags\": [\n          \"Customer\"\n        ],\n        \"requestBody\": {\n          \"content\": {\n            \"application/json\": {\n              \"schema\": {\n                \"$ref\": \"#/components/schemas/CustomerDto\"\n              }\n            },\n            \"text/json\": {\n              \"schema\": {\n                \"$ref\": \"#/components/schemas/CustomerDto\"\n              }\n            },\n            \"application/*+json\": {\n              \"schema\": {\n                \"$ref\": \"#/components/schemas/CustomerDto\"\n              }\n            }\n          }\n        },\n        \"responses\": {\n          \"200\": {\n            \"description\": \"Success\",\n            \"content\": {\n              \"text/plain\": {\n                \"schema\": {\n                  \"$ref\": \"#/components/schemas/CustomerDtoPaginatedList\"\n                }\n              },\n              \"application/json\": {\n                \"schema\": {\n                  \"$ref\": \"#/components/schemas/CustomerDtoPaginatedList\"\n                }\n              },\n              \"text/json\": {\n                \"schema\": {\n                  \"$ref\": \"#/components/schemas/CustomerDtoPaginatedList\"\n                }\n              }\n            }\n          }\n        }\n      },\n      \"patch\": {\n        \"tags\": [\n          \"Customer\"\n        ],\n        \"requestBody\": {\n          \"content\": {\n            \"application/json\": {\n              \"schema\": {\n                \"$ref\": \"#/components/schemas/CustomerDto\"\n              }\n            },\n            \"text/json\": {\n              \"schema\": {\n                \"$ref\": \"#/components/schemas/CustomerDto\"\n              }\n            },\n            \"application/*+json\": {\n              \"schema\": {\n                \"$ref\": \"#/components/schemas/CustomerDto\"\n              }\n            }\n          }\n        },\n        \"responses\": {\n          \"200\": {\n            \"description\": \"Success\",\n            \"content\": {\n              \"text/plain\": {\n                \"schema\": {\n                  \"$ref\": \"#/components/schemas/CustomerDto\"\n                }\n              },\n              \"application/json\": {\n                \"schema\": {\n                  \"$ref\": \"#/components/schemas/CustomerDto\"\n                }\n              },\n              \"text/json\": {\n                \"schema\": {\n                  \"$ref\": \"#/components/schemas/CustomerDto\"\n                }\n              }\n            }\n          }\n        }\n      },\n      \"delete\": {\n        \"tags\": [\n          \"Customer\"\n        ],\n        \"parameters\": [\n          {\n            \"name\": \"id\",\n            \"in\": \"query\",\n            \"schema\": {\n              \"type\": \"string\",\n              \"format\": \"uuid\"\n            }\n          }\n        ],\n        \"responses\": {\n          \"200\": {\n            \"description\": \"Success\"\n          }\n        }\n      }\n    },\n    \"/api/User\": {\n      \"get\": {\n        \"tags\": [\n          \"User\"\n        ],\n        \"parameters\": [\n          {\n            \"name\": \"id\",\n            \"in\": \"query\",\n            \"schema\": {\n              \"type\": \"string\"\n            }\n          }\n        ],\n        \"responses\": {\n          \"200\": {\n            \"description\": \"Success\"\n          }\n        }\n      },\n      \"patch\": {\n        \"tags\": [\n          \"User\"\n        ],\n        \"requestBody\": {\n          \"content\": {\n            \"application/json\": {\n              \"schema\": {\n                \"$ref\": \"#/components/schemas/UserDto\"\n              }\n            },\n            \"text/json\": {\n              \"schema\": {\n                \"$ref\": \"#/components/schemas/UserDto\"\n              }\n            },\n            \"application/*+json\": {\n              \"schema\": {\n                \"$ref\": \"#/components/schemas/UserDto\"\n              }\n            }\n          }\n        },\n        \"responses\": {\n          \"200\": {\n            \"description\": \"Success\"\n          }\n        }\n      },\n      \"delete\": {\n        \"tags\": [\n          \"User\"\n        ],\n        \"requestBody\": {\n          \"content\": {\n            \"application/json\": {\n              \"schema\": {\n                \"$ref\": \"#/components/schemas/UserDto\"\n              }\n            },\n            \"text/json\": {\n              \"schema\": {\n                \"$ref\": \"#/components/schemas/UserDto\"\n              }\n            },\n            \"application/*+json\": {\n              \"schema\": {\n                \"$ref\": \"#/components/schemas/UserDto\"\n              }\n            }\n          }\n        },\n        \"responses\": {\n          \"200\": {\n            \"description\": \"Success\"\n          }\n        }\n      }\n    }\n  },\n  \"components\": {\n    \"schemas\": {\n      \"ArticleGroupDto\": {\n        \"type\": \"object\",\n        \"properties\": {\n          \"id\": {\n            \"type\": \"string\",\n            \"format\": \"uuid\"\n          },\n          \"name\": {\n            \"type\": \"string\",\n            \"nullable\": true\n          },\n          \"articlegroupdto\": {\n            \"$ref\": \"#/components/schemas/ArticleGroupDto\"\n          }\n        },\n        \"additionalProperties\": false\n      },\n      \"ArticleGroupDtoPaginatedList\": {\n        \"type\": \"object\",\n        \"properties\": {\n          \"currentPage\": {\n            \"type\": \"integer\",\n            \"format\": \"int32\"\n          },\n          \"totalPages\": {\n            \"type\": \"integer\",\n            \"format\": \"int32\"\n          },\n          \"pageSize\": {\n            \"type\": \"integer\",\n            \"format\": \"int32\"\n          },\n          \"totalCount\": {\n            \"type\": \"integer\",\n            \"format\": \"int32\"\n          },\n          \"firstRowOnPage\": {\n            \"type\": \"integer\",\n            \"format\": \"int32\",\n            \"readOnly\": true\n          },\n          \"lastRowOnPage\": {\n            \"type\": \"integer\",\n            \"format\": \"int32\",\n            \"readOnly\": true\n          },\n          \"hasPrevious\": {\n            \"type\": \"boolean\",\n            \"readOnly\": true\n          },\n          \"hasNext\": {\n            \"type\": \"boolean\",\n            \"readOnly\": true\n          },\n          \"results\": {\n            \"type\": \"array\",\n            \"items\": {\n              \"$ref\": \"#/components/schemas/ArticleGroupDto\"\n            },\n            \"nullable\": true\n          }\n        },\n        \"additionalProperties\": false\n      },\n      \"AuthenticatedMessage\": {\n        \"type\": \"object\",\n        \"properties\": {\n          \"message\": {\n            \"type\": \"string\",\n            \"nullable\": true\n          },\n          \"status\": {\n            \"type\": \"string\",\n            \"nullable\": true,\n            \"readOnly\": true\n          },\n          \"token\": {\n            \"nullable\": true\n          }\n        },\n        \"additionalProperties\": false\n      },\n      \"Credentials\": {\n        \"type\": \"object\",\n        \"properties\": {\n          \"username\": {\n            \"type\": \"string\",\n            \"nullable\": true\n          },\n          \"password\": {\n            \"type\": \"string\",\n            \"nullable\": true\n          }\n        },\n        \"additionalProperties\": false\n      },\n      \"CustomerDto\": {\n        \"type\": \"object\",\n        \"properties\": {\n          \"id\": {\n            \"type\": \"string\",\n            \"format\": \"uuid\"\n          },\n          \"customerNr\": {\n            \"type\": \"integer\",\n            \"format\": \"int32\"\n          },\n          \"firstname\": {\n            \"type\": \"string\",\n            \"nullable\": true\n          },\n          \"lastname\": {\n            \"type\": \"string\",\n            \"nullable\": true\n          },\n          \"website\": {\n            \"type\": \"string\",\n            \"nullable\": true\n          },\n          \"userId\": {\n            \"type\": \"string\",\n            \"nullable\": true\n          }\n        },\n        \"additionalProperties\": false\n      },\n      \"CustomerDtoPaginatedList\": {\n        \"type\": \"object\",\n        \"properties\": {\n          \"currentPage\": {\n            \"type\": \"integer\",\n            \"format\": \"int32\"\n          },\n          \"totalPages\": {\n            \"type\": \"integer\",\n            \"format\": \"int32\"\n          },\n          \"pageSize\": {\n            \"type\": \"integer\",\n            \"format\": \"int32\"\n          },\n          \"totalCount\": {\n            \"type\": \"integer\",\n            \"format\": \"int32\"\n          },\n          \"firstRowOnPage\": {\n            \"type\": \"integer\",\n            \"format\": \"int32\",\n            \"readOnly\": true\n          },\n          \"lastRowOnPage\": {\n            \"type\": \"integer\",\n            \"format\": \"int32\",\n            \"readOnly\": true\n          },\n          \"hasPrevious\": {\n            \"type\": \"boolean\",\n            \"readOnly\": true\n          },\n          \"hasNext\": {\n            \"type\": \"boolean\",\n            \"readOnly\": true\n          },\n          \"results\": {\n            \"type\": \"array\",\n            \"items\": {\n              \"$ref\": \"#/components/schemas/CustomerDto\"\n            },\n            \"nullable\": true\n          }\n        },\n        \"additionalProperties\": false\n      },\n      \"SuccessMessage\": {\n        \"type\": \"object\",\n        \"properties\": {\n          \"message\": {\n            \"type\": \"string\",\n            \"nullable\": true\n          },\n          \"status\": {\n            \"type\": \"string\",\n            \"nullable\": true,\n            \"readOnly\": true\n          }\n        },\n        \"additionalProperties\": false\n      },\n      \"UserDetails\": {\n        \"required\": [\n          \"email\",\n          \"password\",\n          \"userName\"\n        ],\n        \"type\": \"object\",\n        \"properties\": {\n          \"userName\": {\n            \"type\": \"string\"\n          },\n          \"password\": {\n            \"type\": \"string\"\n          },\n          \"email\": {\n            \"type\": \"string\"\n          }\n        },\n        \"additionalProperties\": false\n      },\n      \"UserDto\": {\n        \"type\": \"object\",\n        \"properties\": {\n          \"id\": {\n            \"type\": \"string\",\n            \"format\": \"uuid\"\n          },\n          \"userName\": {\n            \"type\": \"string\",\n            \"nullable\": true\n          },\n          \"email\": {\n            \"type\": \"string\",\n            \"nullable\": true\n          },\n          \"password\": {\n            \"type\": \"string\",\n            \"nullable\": true\n          },\n          \"assignedCustomers\": {\n            \"type\": \"array\",\n            \"items\": {\n              \"$ref\": \"#/components/schemas/CustomerDto\"\n            },\n            \"nullable\": true\n          }\n        },\n        \"additionalProperties\": false\n      }\n    },\n    \"securitySchemes\": {\n      \"Bearer\": {\n        \"type\": \"apiKey\",\n        \"description\": \"JWT Authorization header using the Bearer scheme. Example: \\\"Authorization: Bearer {token}\\\"\",\n        \"name\": \"Authorization\",\n        \"in\": \"header\"\n      }\n    }\n  },\n  \"security\": [\n    { }\n  ]\n}","contentType":"yaml","_type":"api_spec"},{"_id":"env_ea9e37039e3340d094de8da03f1d7edb","parentId":"env_28900db254353dc1291e02c305f0840509756016","modified":1631025925575,"created":1629317330531,"name":"Development - User","data":{"Username":"testuser","Password":"Test@1","BaseUrl":"http://localhost:5000"},"dataPropertyOrder":{"&":["Username","Password","BaseUrl"]},"color":"#48cd23","isPrivate":false,"metaSortKey":1629317330531,"_type":"environment"},{"_id":"env_697e7cf2ec5e4ab78d01b434dcf19c6e","parentId":"env_28900db254353dc1291e02c305f0840509756016","modified":1631025945675,"created":1631025927942,"name":"Development - Administrator","data":{"Username":"testadministrator","Password":"Test@1","BaseUrl":"http://localhost:5000"},"dataPropertyOrder":{"&":["Username","Password","BaseUrl"]},"color":"#e024c1","isPrivate":false,"metaSortKey":1629317330556,"_type":"environment"}]}